_mecab.cpython-38-x86_64-linux-gnu.so
mecab/__init__.py
mecab/mecabrc
mecab/mecab.py
mecab/__main__.py
mecab/types.py
mecab/utils.py
mecab/pybind/_mecab/utils.h
python_mecab_ko-1.3.7.dist-info/LICENSE
python_mecab_ko-1.3.7.dist-info/WHEEL
python_mecab_ko-1.3.7.dist-info/top_level.txt
python_mecab_ko-1.3.7.dist-info/RECORD
python_mecab_ko-1.3.7.dist-info/METADATA
python_mecab_ko.libs/libmecab-7d53eea1.so.2.0.0
