Metadata-Version: 2.1
Name: python-mecab-ko
Version: 1.3.7
Summary: A python binding for mecab-ko
Home-page: https://github.com/jonghwanhyeon/python-mecab-ko
Author: Jonghwan Hyeon
Author-email: jonghwanhyeon93@gmail.com
License: BSD 3-Clause License
Keywords: mecab,mecab-ko
Classifier: Development Status :: 4 - Beta
Classifier: Intended Audience :: Science/Research
Classifier: License :: OSI Approved :: BSD License
Classifier: Natural Language :: Korean
Classifier: Programming Language :: Python :: 3
Classifier: Programming Language :: Python :: 3 :: Only
Classifier: Topic :: Text Processing
Classifier: Topic :: Text Processing :: Linguistic
Requires-Python: >=3.7
License-File: LICENSE
Requires-Dist: python-mecab-ko-dic
